pre_release/__init__.py
pre_release-0.0.1a1.dist-info/METADATA
pre_release-0.0.1a1.dist-info/WHEEL
pre_release-0.0.1a1.dist-info/RECORD
